edgeberry/__init__.py
edgeberry/edgeberry.py
edgeberry/edgeberry_cloudconnect.py
edgeberry-0.1.2.dist-info/LICENSE.txt
edgeberry-0.1.2.dist-info/METADATA
edgeberry-0.1.2.dist-info/WHEEL
edgeberry-0.1.2.dist-info/top_level.txt
edgeberry-0.1.2.dist-info/RECORD
