Metadata-Version: 2.1
Name: edgeberry
Version: 0.1.2
Summary: Python SDK for interfacing applications with Edgeberry
Home-page: https://github.com/Edgeberry/Edgeberry-Python-SDK
Author: Sanne 'SpuQ' Santens
Author-email: sanne.santens@gmail.com
Classifier: Programming Language :: Python :: 3
Classifier: License :: OSI Approved :: MIT License
Classifier: Operating System :: OS Independent
Requires-Python: >=3.6
License-File: LICENSE.txt
Requires-Dist: pydbus
Requires-Dist: PyGObject
